launch/__init__.py
launch/env.py
launch/update.py
launch/cli/__init__.py
launch/cli/entrypoint.py
launch/cli/common/__init__.py
launch/cli/common/options/__init__.py
launch/cli/common/options/aws.py
launch/cli/github/__init__.py
launch/cli/github/access/__init__.py
launch/cli/github/access/commands.py
launch/cli/github/auth/__init__.py
launch/cli/github/auth/commands.py
launch/cli/github/commit/__init__.py
launch/cli/github/commit/status.py
launch/cli/github/hooks/__init__.py
launch/cli/github/hooks/commands.py
launch/cli/github/repo/__init__.py
launch/cli/github/repo/commands.py
launch/cli/github/version/__init__.py
launch/cli/github/version/commands.py
launch/cli/helm/__init__.py
launch/cli/helm/commands.py
launch/cli/j2/__init__.py
launch/cli/j2/render/__init__.py
launch/cli/service/__init__.py
launch/cli/service/build/__init__.py
launch/cli/service/clean/__init__.py
launch/cli/service/create/__init__.py
launch/cli/service/generate/__init__.py
launch/cli/service/publish/__init__.py
launch/cli/service/test/__init__.py
launch/cli/service/update/__init__.py
launch/cli/terragrunt/__init__.py
launch/cli/validate/__init__.py
launch/cli/validate/commands.py
launch/config/ado.py
launch/config/aws.py
launch/config/common.py
launch/config/container.py
launch/config/github.py
launch/config/launchconfig.py
launch/config/terraform.py
launch/config/terragrunt.py
launch/config/webhook.py
launch/constants/__init__.py
launch/constants/common.py
launch/constants/github.py
launch/constants/launchconfig.py
launch/constants/version.py
launch/enums/launchconfig.py
launch/lib/__init__.py
launch/lib/automation/__init__.py
launch/lib/automation/common/__init__.py
launch/lib/automation/common/functions.py
launch/lib/automation/environment/__init__.py
launch/lib/automation/environment/functions.py
launch/lib/automation/helm/__init__.py
launch/lib/automation/helm/functions.py
launch/lib/automation/processes/__init__.py
launch/lib/automation/processes/functions.py
launch_cli-0.15.1.dist-info/LICENSE
launch_cli-0.15.1.dist-info/METADATA
launch_cli-0.15.1.dist-info/WHEEL
launch_cli-0.15.1.dist-info/entry_points.txt
launch_cli-0.15.1.dist-info/top_level.txt
launch_cli-0.15.1.dist-info/RECORD
