Metadata-Version: 2.2
Name: launch-cli
Version: 0.15.1
Summary: CLI tooling for common Launch functions
License: Apache 2.0
Project-URL: Homepage, https://github.com/launchbynttdata/launch-cli
Project-URL: Issues, https://github.com/launchbynttdata/launch-cli/issues
Classifier: Programming Language :: Python :: 3
Classifier: License :: OSI Approved :: MIT License
Classifier: Operating System :: OS Independent
Requires-Python: >=3.11
License-File: LICENSE
Requires-Dist: boto3>=1.34.135
Requires-Dist: click-spinner>=0.1.10
Requires-Dist: click>=8.1.7
Requires-Dist: gitpython>=3.1
Requires-Dist: Jinja2>=3.1.3
Requires-Dist: pygithub>=2.1.1
Requires-Dist: pytest-cov>=6.0.0
Requires-Dist: ruamel.yaml>=0.17.32
Requires-Dist: semver>=3.0
Provides-Extra: dev
Requires-Dist: pytest~=7.0; extra == "dev"
Requires-Dist: pytest-mock~=3.0; extra == "dev"
Requires-Dist: responses~=0.24.0; extra == "dev"
Requires-Dist: black>=23.11.0; extra == "dev"
Requires-Dist: isort>=5.12.0; extra == "dev"
Requires-Dist: faker>=24.14; extra == "dev"
